keysort/__init__.py
keysort/keysort.py
Keysort-0.1.3.dist-info/LICENSE
Keysort-0.1.3.dist-info/METADATA
Keysort-0.1.3.dist-info/WHEEL
Keysort-0.1.3.dist-info/top_level.txt
Keysort-0.1.3.dist-info/RECORD
