Metadata-Version: 2.1
Name: Keysort
Version: 0.1.3
Summary: A small utility for sorting lists of dictionaries by dictionary key
Home-page: https://github.com/nkantar/Keysort
Author: Nik Kantar
Author-email: nik@nkantar.com
License: UNKNOWN
Platform: UNKNOWN
